[{"__type__":"cc.SpriteFrame","content":{"name":"button-rank","texture":"42vyK8lmtEBL6d7t0mksoo","rect":[0,163,140,68],"offset":[0,0],"originalSize":[140,68],"capInsets":[0,0,0,0]}},{"__type__":"cc.SpriteFrame","content":{"name":"button-select-line","texture":"42vyK8lmtEBL6d7t0mksoo","rect":[0,308,170,146],"offset":[0,0],"originalSize":[170,146],"capInsets":[0,0,0,0]}},{"__type__":"cc.SpriteFrame","content":{"name":"button-1","texture":"42vyK8lmtEBL6d7t0mksoo","rect":[51,0,35,36],"offset":[0,0],"originalSize":[35,36],"capInsets":[0,0,0,0]}},{"__type__":"cc.SpriteFrame","content":{"name":"txt-history","texture":"42vyK8lmtEBL6d7t0mksoo","rect":[382,0,123,45],"offset":[0,0],"originalSize":[123,45],"capInsets":[0,0,0,0]}},{"__type__":"cc.SpriteFrame","content":{"name":"button-spin","texture":"42vyK8lmtEBL6d7t0mksoo","rect":[439,163,227,145],"offset":[0,0],"originalSize":[227,145],"capInsets":[0,0,0,0]}},{"__type__":"cc.SpriteFrame","content":{"name":"button-auto-stop","texture":"42vyK8lmtEBL6d7t0mksoo","rect":[361,96,182,64],"offset":[0,0],"originalSize":[182,64],"capInsets":[0,0,0,0]}},{"__type__":"cc.SpriteFrame","content":{"name":"button-setting","texture":"42vyK8lmtEBL6d7t0mksoo","rect":[140,163,72,72],"offset":[0,0],"originalSize":[72,72],"capInsets":[0,0,0,0]}},{"__type__":"cc.SpriteFrame","content":{"name":"bg-prize","texture":"42vyK8lmtEBL6d7t0mksoo","rect":[0,511,636,417],"offset":[0,0],"originalSize":[636,417],"capInsets":[0,0,0,0]}},{"__type__":"cc.SpriteFrame","content":{"name":"txt-select-line","texture":"42vyK8lmtEBL6d7t0mksoo","rect":[265,46,178,48],"offset":[0,0],"originalSize":[178,48],"capInsets":[0,0,0,0]}},{"__type__":"cc.SpriteFrame","content":{"name":"button-close","texture":"42vyK8lmtEBL6d7t0mksoo","rect":[334,0,48,45],"offset":[0,0],"originalSize":[48,45],"capInsets":[0,0,0,0]}},{"__type__":"cc.SpriteFrame","content":{"name":"bg-select-line","texture":"42vyK8lmtEBL6d7t0mksoo","rect":[295,0,39,39],"offset":[0,0],"originalSize":[39,39],"capInsets":[0,0,0,0]}},{"__type__":"cc.SpriteFrame","content":{"name":"button-2","texture":"42vyK8lmtEBL6d7t0mksoo","rect":[86,0,35,36],"offset":[0,0],"originalSize":[35,36],"capInsets":[0,0,0,0]}},{"__type__":"cc.SpriteFrame","content":{"name":"button-free-spin","texture":"42vyK8lmtEBL6d7t0mksoo","rect":[212,163,227,145],"offset":[0,0],"originalSize":[227,145],"capInsets":[0,0,0,0]}},{"__type__":"cc.SpriteFrame","content":{"name":"toggle-bg","texture":"42vyK8lmtEBL6d7t0mksoo","rect":[0,0,21,19],"offset":[0,0],"originalSize":[21,19],"capInsets":[0,0,0,0]}},{"__type__":"cc.SpriteFrame","content":{"name":"button-auto","texture":"42vyK8lmtEBL6d7t0mksoo","rect":[0,96,182,64],"offset":[0,0],"originalSize":[182,64],"capInsets":[0,0,0,0]}},{"__type__":"cc.SpriteFrame","content":{"name":"button-prize","texture":"42vyK8lmtEBL6d7t0mksoo","rect":[182,96,179,64],"offset":[0,0],"originalSize":[179,64],"capInsets":[0,0,0,0]}},{"__type__":"cc.SpriteFrame","content":{"name":"button-test","texture":"42vyK8lmtEBL6d7t0mksoo","rect":[315,308,147,203],"offset":[0,0],"originalSize":[147,203],"capInsets":[0,0,0,0]}},{"__type__":"cc.SpriteFrame","content":{"name":"button-odd","texture":"42vyK8lmtEBL6d7t0mksoo","rect":[505,0,122,46],"offset":[0,0],"originalSize":[122,46],"capInsets":[0,0,0,0]}},{"__type__":"cc.SpriteFrame","content":{"name":"txt-rank","texture":"42vyK8lmtEBL6d7t0mksoo","rect":[121,0,174,39],"offset":[0,0],"originalSize":[174,39],"capInsets":[0,0,0,0]}},{"__type__":"cc.SpriteFrame","content":{"name":"button-even","texture":"42vyK8lmtEBL6d7t0mksoo","rect":[0,46,164,47],"offset":[0,0],"originalSize":[164,47],"capInsets":[0,0,0,0]}},{"__type__":"cc.SpriteFrame","content":{"name":"button-play","texture":"42vyK8lmtEBL6d7t0mksoo","rect":[170,308,145,201],"offset":[0,0],"originalSize":[145,201],"capInsets":[0,0,0,0]}},{"__type__":"cc.SpriteFrame","content":{"name":"button-add-minus","texture":"42vyK8lmtEBL6d7t0mksoo","rect":[21,0,30,34],"offset":[0,0],"originalSize":[30,34],"capInsets":[0,0,0,0]}},{"__type__":"cc.SpriteFrame","content":{"name":"button-back","texture":"42vyK8lmtEBL6d7t0mksoo","rect":[543,96,74,67],"offset":[0,0],"originalSize":[74,67],"capInsets":[0,0,0,0]}},{"__type__":"cc.SpriteFrame","content":{"name":"button-all","texture":"42vyK8lmtEBL6d7t0mksoo","rect":[164,46,101,48],"offset":[0,0],"originalSize":[101,48],"capInsets":[0,0,0,0]}},{"__type__":"cc.SpriteFrame","content":{"name":"button-cancel","texture":"42vyK8lmtEBL6d7t0mksoo","rect":[443,46,128,50],"offset":[0,0],"originalSize":[128,50],"capInsets":[0,0,0,0]}}]