[{"__type__":"cc.Prefab","_name":"itemNews","data":{"__id__":1}},{"__type__":"cc.Node","_name":"itemNews","_children":[{"__id__":2},{"__id__":4},{"__id__":6},{"__id__":8},{"__id__":10},{"__id__":11}],"_components":[{"__type__":"cc.Layout","node":{"__id__":1},"_layoutSize":{"__type__":"cc.Size","width":513.3299999999999,"height":30},"_resize":1,"_N$layoutType":1,"_N$spacingX":4},{"__type__":"ed1c0NxAXlNI4ktSR1Kq45Q","node":{"__id__":1},"status":{"__id__":3},"users":{"__id__":5},"win":{"__id__":7},"bet":{"__id__":9},"game":{"__id__":12}}],"_prefab":{"__type__":"cc.PrefabInfo","root":{"__id__":1},"asset":{"__uuid__":"cdNaxUs25K3aLBTdngKPX/"},"fileId":"412Dq42kxMcYGYlQOe+SiX"},"_contentSize":{"__type__":"cc.Size","width":513.3299999999999,"height":30},"_trs":{"__type__":"TypedArray","ctor":"Float64Array","array":[0,0,0,0,0,0,1,1,1,1]}},{"__type__":"cc.Node","_name":"status","_parent":{"__id__":1},"_components":[{"__id__":3}],"_prefab":{"__type__":"cc.PrefabInfo","root":{"__id__":1},"asset":{"__uuid__":"cdNaxUs25K3aLBTdngKPX/"},"fileId":"95+rSfkJJOGqExKGpNF0Ba"},"_color":{"__type__":"cc.Color","r":255},"_contentSize":{"__type__":"cc.Size","width":125.33,"height":30},"_trs":{"__type__":"TypedArray","ctor":"Float64Array","array":[-193.99999999999997,0,0,0,0,0,1,1,1,1]}},{"__type__":"cc.Label","node":{"__id__":2},"_materials":[{"__uuid__":"ecpdLyjvZBwrvm+cedCcQy"}],"_useOriginalSize":false,"_string":"(Thắng Lớn)","_N$string":"(Thắng Lớn)","_fontSize":20,"_lineHeight":45,"_N$file":{"__uuid__":"1fE+pG2OZHWY0AzVNb+rOn"},"_isSystemFontUsed":false,"_N$horizontalAlign":1},{"__type__":"cc.Node","_name":"username","_parent":{"__id__":1},"_components":[{"__id__":5}],"_prefab":{"__type__":"cc.PrefabInfo","root":{"__id__":1},"asset":{"__uuid__":"cdNaxUs25K3aLBTdngKPX/"},"fileId":"1f1EcVJqNPxrkdNV0ubgWt"},"_color":{"__type__":"cc.Color","r":255,"g":255},"_contentSize":{"__type__":"cc.Size","width":124,"height":29.33},"_trs":{"__type__":"TypedArray","ctor":"Float64Array","array":[-65.33499999999998,0,0,0,0,0,1,1,1,1]}},{"__type__":"cc.Label","node":{"__id__":4},"_materials":[{"__uuid__":"ecpdLyjvZBwrvm+cedCcQy"}],"_useOriginalSize":false,"_string":"Thinhdeptry","_N$string":"Thinhdeptry","_fontSize":20,"_lineHeight":44,"_N$file":{"__uuid__":"1fE+pG2OZHWY0AzVNb+rOn"},"_isSystemFontUsed":false,"_N$horizontalAlign":1},{"__type__":"cc.Node","_name":"win","_parent":{"__id__":1},"_components":[{"__id__":7}],"_prefab":{"__type__":"cc.PrefabInfo","root":{"__id__":1},"asset":{"__uuid__":"cdNaxUs25K3aLBTdngKPX/"},"fileId":"15KLlMFKBFyJaC47Mx5RPP"},"_contentSize":{"__type__":"cc.Size","width":62,"height":31.33},"_trs":{"__type__":"TypedArray","ctor":"Float64Array","array":[31.66500000000002,0,0,0,0,0,1,1,1,1]}},{"__type__":"cc.Label","node":{"__id__":6},"_materials":[{"__uuid__":"ecpdLyjvZBwrvm+cedCcQy"}],"_useOriginalSize":false,"_string":"thắng","_N$string":"thắng","_fontSize":20,"_lineHeight":47,"_N$file":{"__uuid__":"1fE+pG2OZHWY0AzVNb+rOn"},"_isSystemFontUsed":false,"_N$horizontalAlign":1},{"__type__":"cc.Node","_name":"bet","_parent":{"__id__":1},"_components":[{"__id__":9}],"_prefab":{"__type__":"cc.PrefabInfo","root":{"__id__":1},"asset":{"__uuid__":"cdNaxUs25K3aLBTdngKPX/"},"fileId":"26EnmiF9VO+K36vv1kVWCB"},"_color":{"__type__":"cc.Color","r":255,"g":255},"_contentSize":{"__type__":"cc.Size","width":71.33,"height":29.33},"_trs":{"__type__":"TypedArray","ctor":"Float64Array","array":[102.33000000000001,0,0,0,0,0,1,1,1,1]}},{"__type__":"cc.Label","node":{"__id__":8},"_materials":[{"__uuid__":"ecpdLyjvZBwrvm+cedCcQy"}],"_useOriginalSize":false,"_string":"10.000","_N$string":"10.000","_fontSize":20,"_lineHeight":44,"_N$file":{"__uuid__":"1fE+pG2OZHWY0AzVNb+rOn"},"_isSystemFontUsed":false,"_N$horizontalAlign":1},{"__type__":"cc.Node","_name":"gamet","_parent":{"__id__":1},"_components":[{"__type__":"cc.Label","node":{"__id__":10},"_materials":[{"__uuid__":"ecpdLyjvZBwrvm+cedCcQy"}],"_useOriginalSize":false,"_string":"game","_N$string":"game","_fontSize":20,"_lineHeight":47,"_N$file":{"__uuid__":"1fE+pG2OZHWY0AzVNb+rOn"},"_isSystemFontUsed":false,"_N$horizontalAlign":1}],"_prefab":{"__type__":"cc.PrefabInfo","root":{"__id__":1},"asset":{"__uuid__":"cdNaxUs25K3aLBTdngKPX/"},"fileId":"66pAlg+ohPGIG1S0HJcg+P"},"_contentSize":{"__type__":"cc.Size","width":62.67,"height":31.33},"_trs":{"__type__":"TypedArray","ctor":"Float64Array","array":[173.33,0,0,0,0,0,1,1,1,1]}},{"__type__":"cc.Node","_name":"game","_parent":{"__id__":1},"_components":[{"__id__":12}],"_prefab":{"__type__":"cc.PrefabInfo","root":{"__id__":1},"asset":{"__uuid__":"cdNaxUs25K3aLBTdngKPX/"},"fileId":"28OVcOyKlMR4xfq5jpuTtR"},"_color":{"__type__":"cc.Color","r":82,"g":255},"_contentSize":{"__type__":"cc.Size","width":48,"height":29.33},"_trs":{"__type__":"TypedArray","ctor":"Float64Array","array":[232.66500000000002,0,0,0,0,0,1,1,1,1]}},{"__type__":"cc.Label","node":{"__id__":11},"_materials":[{"__uuid__":"ecpdLyjvZBwrvm+cedCcQy"}],"_useOriginalSize":false,"_string":"Zeus","_N$string":"Zeus","_fontSize":20,"_lineHeight":44,"_N$file":{"__uuid__":"1fE+pG2OZHWY0AzVNb+rOn"},"_isSystemFontUsed":false,"_N$horizontalAlign":1}]